rl4co/__init__.py
rl4co/data/__init__.py
rl4co/data/dataset.py
rl4co/data/generate_data.py
rl4co/data/transforms.py
rl4co/data/utils.py
rl4co/envs/__init__.py
rl4co/envs/common/__init__.py
rl4co/envs/common/base.py
rl4co/envs/common/distribution_utils.py
rl4co/envs/common/utils.py
rl4co/envs/eda/__init__.py
rl4co/envs/eda/dpp/env.py
rl4co/envs/eda/dpp/generator.py
rl4co/envs/eda/dpp/render.py
rl4co/envs/eda/mdpp/env.py
rl4co/envs/eda/mdpp/generator.py
rl4co/envs/eda/mdpp/render.py
rl4co/envs/graph/__init__.py
rl4co/envs/graph/flp/__init__.py
rl4co/envs/graph/flp/env.py
rl4co/envs/graph/flp/generator.py
rl4co/envs/graph/mcp/__init__.py
rl4co/envs/graph/mcp/env.py
rl4co/envs/graph/mcp/generator.py
rl4co/envs/routing/__init__.py
rl4co/envs/routing/atsp/env.py
rl4co/envs/routing/atsp/generator.py
rl4co/envs/routing/atsp/render.py
rl4co/envs/routing/cvrp/README.md
rl4co/envs/routing/cvrp/env.py
rl4co/envs/routing/cvrp/generator.py
rl4co/envs/routing/cvrp/local_search.py
rl4co/envs/routing/cvrp/render.py
rl4co/envs/routing/cvrpmvc/env.py
rl4co/envs/routing/cvrptw/env.py
rl4co/envs/routing/cvrptw/generator.py
rl4co/envs/routing/cvrptw/render.py
rl4co/envs/routing/mdcpdp/env.py
rl4co/envs/routing/mdcpdp/generator.py
rl4co/envs/routing/mdcpdp/render.py
rl4co/envs/routing/mpdp/env.py
rl4co/envs/routing/mpdp/generator.py
rl4co/envs/routing/mpdp/render.py
rl4co/envs/routing/mtsp/env.py
rl4co/envs/routing/mtsp/generator.py
rl4co/envs/routing/mtsp/render.py
rl4co/envs/routing/mtvrp/env.py
rl4co/envs/routing/mtvrp/generator.py
rl4co/envs/routing/mtvrp/render.py
rl4co/envs/routing/mtvrp/baselines/constants.py
rl4co/envs/routing/mtvrp/baselines/lkh.py
rl4co/envs/routing/mtvrp/baselines/ortools.py
rl4co/envs/routing/mtvrp/baselines/pyvrp.py
rl4co/envs/routing/mtvrp/baselines/solve.py
rl4co/envs/routing/mtvrp/baselines/utils.py
rl4co/envs/routing/op/env.py
rl4co/envs/routing/op/generator.py
rl4co/envs/routing/op/render.py
rl4co/envs/routing/pctsp/env.py
rl4co-0.6.0.dist-info/METADATA
rl4co-0.6.0.dist-info/WHEEL
rl4co-0.6.0.dist-info/licenses/LICENSE
rl4co-0.6.0.dist-info/RECORD
