Metadata-Version: 2.4
Name: rl4co
Version: 0.6.0
Summary: RL4CO: an Extensive Reinforcement Learning for Combinatorial Optimization Benchmark
Project-URL: Homepage, https://rl4.co
Project-URL: Repository, https://github.com/ai4co/rl4co
Project-URL: Documentation, https://rl4co.readthedocs.io
Project-URL: Tracker, https://github.com/ai4co/rl4co/issues
Author: Yining Ma, Fanchen Bu, Jiarui Wang, Haoran Ye, Minsu Kim, Sanghyeok Choi, Zepeda Gast, Andre Hottung, Jianan Zhou, Jieyi Bi, Yu Hu, Fei Liu, Hyeonah Kim, Jiwoo Son, Haeyeon Kim, Davide Angioni, Wouter Kool, Zhiguang Cao, Jie Zhang, Kijung Shin, Cathy Wu, Sungsoo Ahn, Guojie Song, Changhyun Kwon, Lin Xie, Jinkyoo Park, AI4CO
Author-email: Federico Berto <berto.federico2@gmail.com>, Chuanbo Hua <cbhua@kaist.ac.kr>, Junyoung Park <junyoungpark.ml@gmail.com>, Laurin Luttmann <laurin.luttmann@gmail.com>
License-Expression: MIT
License-File: LICENSE
Keywords: benchmark,combinatorial optimization,reinforcement learning
Classifier: Development Status :: 4 - Beta
Classifier: Intended Audience :: Developers
Classifier: Intended Audience :: Science/Research
Classifier: License :: OSI Approved :: MIT License
Classifier: Operating System :: OS Independent
Classifier: Programming Language :: Python
Classifier: Programming Language :: Python :: 3
Classifier: Programming Language :: Python :: 3.10
Classifier: Programming Language :: Python :: 3.11
Classifier: Programming Language :: Python :: 3.12
Classifier: Topic :: Scientific/Engineering :: Artificial Intelligence
Requires-Python: >=3.10
Requires-Dist: einops
Requires-Dist: hydra-colorlog
Requires-Dist: hydra-core
Requires-Dist: lightning>=2.1.0
Requires-Dist: matplotlib
Requires-Dist: omegaconf
Requires-Dist: pyrootutils
Requires-Dist: rich
Requires-Dist: robust-downloader
Requires-Dist: scipy
Requires-Dist: tensordict>=0.6.0
Requires-Dist: torchrl>=0.6.0
Requires-Dist: wandb
Provides-Extra: dev
Requires-Dist: black; extra == 'dev'
Requires-Dist: pre-commit>=3.3.3; extra == 'dev'
Requires-Dist: pytest; extra == 'dev'
Requires-Dist: pytest-cov; extra == 'dev'
Requires-Dist: pytest-xdist>=3.7.0; extra == 'dev'
Requires-Dist: ruff; extra == 'dev'
Provides-Extra: docs
Requires-Dist: black; extra == 'docs'
Requires-Dist: griffe; extra == 'docs'
Requires-Dist: griffe-inherited-docstrings; extra == 'docs'
Requires-Dist: griffe-typingdoc; extra == 'docs'
Requires-Dist: markdown-gfm-admonition; extra == 'docs'
Requires-Dist: mdx-breakless-lists; extra == 'docs'
Requires-Dist: mdx-truly-sane-lists; extra == 'docs'
Requires-Dist: mike; extra == 'docs'
Requires-Dist: mkdocs; extra == 'docs'
Requires-Dist: mkdocs-autolinks-plugin; extra == 'docs'
Requires-Dist: mkdocs-jupyter; extra == 'docs'
Requires-Dist: mkdocs-material; extra == 'docs'
Requires-Dist: mkdocs-redirects; extra == 'docs'
Requires-Dist: mkdocs-same-dir; extra == 'docs'
Requires-Dist: mkdocstrings-python; extra == 'docs'
Provides-Extra: graph
Requires-Dist: torch-geometric; extra == 'graph'
Provides-Extra: routing
Requires-Dist: numba>=0.58.1; extra == 'routing'
Requires-Dist: pyvrp>=0.9.0; (python_version < '4.0') and extra == 'routing'
